bm25_pt/__init__.py
bm25_pt/bm25.py
bm25_pt-0.0.7.dist-info/LICENSE.txt
bm25_pt-0.0.7.dist-info/METADATA
bm25_pt-0.0.7.dist-info/WHEEL
bm25_pt-0.0.7.dist-info/top_level.txt
bm25_pt-0.0.7.dist-info/RECORD
