Metadata-Version: 2.1
Name: bm25-pt
Version: 0.0.7
Summary: bm25 search algorithm in pytorch
Author: Jack Morris
Author-email: jxm3@cornell.edu
License-File: LICENSE.txt
Requires-Dist: torch
Requires-Dist: transformers
